pymemeru/__init__.py
pymemeru/aioget.py
pymemeru/models/__init__.py
pymemeru/models/page.py
pymemeru/models/search.py
pymemeru/page.py
pymemeru/popular.py
pymemeru/search.py
pymemeru-0.2.3.dist-info/LICENSE
pymemeru-0.2.3.dist-info/METADATA
pymemeru-0.2.3.dist-info/WHEEL
pymemeru-0.2.3.dist-info/RECORD
