Metadata-Version: 2.1
Name: pymemeru
Version: 0.2.3
Summary: memepedia.ru parser for python
License: MIT
Keywords: memepedia
Author: Daniel Zakharov
Author-email: gzdan734@gmail.com
Requires-Python: >=3.9,<4.0
Classifier: License :: OSI Approved :: MIT License
Classifier: Programming Language :: Python :: 3
Classifier: Programming Language :: Python :: 3.9
Classifier: Programming Language :: Python :: 3.10
Classifier: Programming Language :: Python :: 3.11
Classifier: Programming Language :: Python :: 3.12
Requires-Dist: beautifulsoup4 (>=4.11.1,<5.0.0)
Requires-Dist: httpx (>=0.27.2,<0.28.0)
Requires-Dist: lxml (>=5.2.1,<6.0.0)
Requires-Dist: pydantic (>=2.7.1,<3.0.0)
